[
  {
    "link": "products[0].id",
    "filename": "tshirt-crop-3.jpg",
    "url": "https://image.uniqlo.com/UQ/ST3/id/imagesgoods/446609/item/idgoods_09_446609.jpg?width=1600&impolicy=quality_75|tshirt-crop-3.jpg"
  },
  {
    "link": "products[0].id",
    "filename": "tshirt-crop-2.jpg",
    "url": "https://image.uniqlo.com/UQ/ST3/id/imagesgoods/446609/sub/idgoods_446609_sub6.jpg?width=1600&impolicy=quality_75|tshirt-crop-2.jpg"
  },
  {
    "link": "products[0].id",
    "filename": "tshirt-crop.jpg",
    "url": "https://image.uniqlo.com/UQ/ST3/id/imagesgoods/446609/sub/idgoods_446609_sub7.jpg?width=1600&impolicy=quality_75|tshirt-crop.jpg"
  },
  {
    "link": "products[1].id",
    "filename": "blus-3.jpg",
    "url": "https://image.uniqlo.com/UQ/ST3/id/imagesgoods/446846/item/idgoods_00_446846.jpg?width=1600&impolicy=quality_75|blus-3.jpg"
  },
  {
    "link": "products[1].id",
    "filename": "blus-2.jpg",
    "url": "https://image.uniqlo.com/UQ/ST3/id/imagesgoods/446846/sub/idgoods_446846_sub6.jpg?width=1600&impolicy=quality_75|blus-2.jpg"
  },
  {
    "link": "products[1].id",
    "filename": "blus.jpg",
    "url": "https://image.uniqlo.com/UQ/ST3/id/imagesgoods/446846/sub/idgoods_446846_sub7.jpg?width=1600&impolicy=quality_75|blus.jpg"
  },
  {
    "link": "products[2].id",
    "filename": "kemeja-linen-3.jpg",
    "url": "https://image.uniqlo.com/UQ/ST3/id/imagesgoods/449037/item/idgoods_42_449037.jpg?width=1600&impolicy=quality_75|kemeja-linen-3.jpg"
  },
  {
    "link": "products[2].id",
    "filename": "kemeja-linen-2.jpg",
    "url": "https://image.uniqlo.com/UQ/ST3/id/imagesgoods/449037/sub/idgoods_449037_sub6.jpg?width=1600&impolicy=quality_75|kemeja-linen-2.jpg"
  },
  {
    "link": "products[2].id",
    "filename": "kemeja-linen.jpg",
    "url": "https://image.uniqlo.com/UQ/ST3/id/imagesgoods/449037/sub/idgoods_449037_sub7.jpg?width=1600&impolicy=quality_75|kemeja-linen.jpg"
  },
  {
    "link": "products[3].id",
    "filename": "tshirt-dry-3.jpg",
    "url": "https://image.uniqlo.com/UQ/ST3/AsianCommon/imagesgoods/444996/sub/goods_444996_sub9.jpg?width=1600&impolicy=quality_75|tshirt-dry-3.jpg"
  },
  {
    "link": "products[3].id",
    "filename": "tshirt-dry-2.jpg",
    "url": "https://image.uniqlo.com/UQ/ST3/id/imagesgoods/444996/sub/idgoods_444996_sub6.jpg?width=1600&impolicy=quality_75|tshirt-dry-2.jpg"
  },
  {
    "link": "products[3].id",
    "filename": "tshirt-dry.jpg",
    "url": "https://image.uniqlo.com/UQ/ST3/id/imagesgoods/444996/sub/idgoods_444996_sub7.jpg?width=1600&impolicy=quality_75|tshirt-dry.jpg"
  },
  {
    "link": "products[4].id",
    "filename": "kemeja-broadcloth-3.jpg",
    "url": "https://image.uniqlo.com/UQ/ST3/AsianCommon/imagesgoods/449468/sub/goods_449468_sub9.jpg?width=1600&impolicy=quality_75|kemeja-broadcloth-3.jpg"
  },
  {
    "link": "products[4].id",
    "filename": "kemeja-broadcloth-2.jpg",
    "url": "https://image.uniqlo.com/UQ/ST3/id/imagesgoods/449468/sub/idgoods_449468_sub6.jpg?width=1600&impolicy=quality_75|kemeja-broadcloth-2.jpg"
  },
  {
    "link": "products[4].id",
    "filename": "kemeja-broadcloth.jpg",
    "url": "https://image.uniqlo.com/UQ/ST3/id/imagesgoods/449468/sub/idgoods_449468_sub7.jpg?width=1600&impolicy=quality_75|kemeja-broadcloth.jpg"
  },
  {
    "link": "products[5].id",
    "filename": "kemeja-extra-fine-3.jpg",
    "url": "https://image.uniqlo.com/UQ/ST3/AsianCommon/imagesgoods/448413/sub/goods_448413_sub9.jpg?width=1600&impolicy=quality_75|kemeja-extra-fine-3.jpg"
  },
  {
    "link": "products[5].id",
    "filename": "kemeja-extra-fine-2.jpg",
    "url": "https://image.uniqlo.com/UQ/ST3/id/imagesgoods/448413/sub/idgoods_448413_sub6.jpg?width=1600&impolicy=quality_75|kemeja-extra-fine-2.jpg"
  },
  {
    "link": "products[5].id",
    "filename": "kemeja-extra-fine.jpg",
    "url": "https://image.uniqlo.com/UQ/ST3/id/imagesgoods/448413/sub/idgoods_448413_sub7.jpg?width=1600&impolicy=quality_75|kemeja-extra-fine.jpg"
  },
  {
    "link": "products[6].id",
    "filename": "kacamata-sports-rim-3.jpg",
    "url": "https://image.uniqlo.com/UQ/ST3/AsianCommon/imagesgoods/447027/item/goods_09_447027.jpg?width=1600&impolicy=quality_75|kacamata-sports-rim-3.jpg"
  },
  {
    "link": "products[6].id",
    "filename": "kacamata-sports-rim-2.jpg",
    "url": "https://image.uniqlo.com/UQ/ST3/AsianCommon/imagesgoods/447027/sub/goods_447027_sub18.jpg?width=1600&impolicy=quality_75|kacamata-sports-rim-2.jpg"
  },
  {
    "link": "products[6].id",
    "filename": "kacamata-sports-rim.jpg",
    "url": "https://image.uniqlo.com/UQ/ST3/AsianCommon/imagesgoods/447027/sub/goods_447027_sub19.jpg?width=1600&impolicy=quality_75|kacamata-sports-rim.jpg"
  },
  {
    "link": "products[7].id",
    "filename": "tas-singlstrap-3.jpg",
    "url": "https://image.uniqlo.com/UQ/ST3/AsianCommon/imagesgoods/447015/item/goods_67_447015.jpg?width=1600&impolicy=quality_75|tas-singlstrap-3.jpg"
  },
  {
    "link": "products[7].id",
    "filename": "tas-singlstrap-2.jpg",
    "url": "https://image.uniqlo.com/UQ/ST3/AsianCommon/imagesgoods/447015/sub/goods_447015_sub9.jpg?width=1600&impolicy=quality_75|tas-singlstrap-2.jpg"
  },
  {
    "link": "products[7].id",
    "filename": "tas-singlstrap.jpg",
    "url": "https://image.uniqlo.com/UQ/ST3/AsianCommon/imagesgoods/447015/sub/goods_447015_sub12.jpg?width=1600&impolicy=quality_75|tas-singlstrap.jpg"
  },
  {
    "link": "products[8].id",
    "filename": "kacamata-round-3.jpg",
    "url": "https://image.uniqlo.com/UQ/ST3/AsianCommon/imagesgoods/447018/item/goods_80_447018.jpg?width=1600&impolicy=quality_75kacamata-round-3.jpg"
  },
  {
    "link": "products[8].id",
    "filename": "kacamata-round-2.jpg",
    "url": "https://image.uniqlo.com/UQ/ST3/AsianCommon/imagesgoods/447018/sub/goods_447018_sub19.jpg?width=1600&impolicy=quality_75kacamata-round-2.jpg"
  },
  {
    "link": "products[8].id",
    "filename": "kacamata-round.jpg",
    "url": "https://image.uniqlo.com/UQ/ST3/AsianCommon/imagesgoods/447018/sub/goods_447018_sub17.jpg?width=1600&impolicy=quality_75kacamata-round.jpg"
  }
]
